{"otherData": {},"traceEvents":[{"cat":"function","dur":758069,"name":"glfwInit","ph":"X","pid":0,"tid":1026436109,"ts":1011308903927},{"cat":"function","dur":563109,"name":"glfwCreateWindow","ph":"X","pid":0,"tid":1026436109,"ts":1011309663742},{"cat":"function","dur":11195,"name":"void __cdecl Hazel::OpenGLContext::Init(void)","ph":"X","pid":0,"tid":1026436109,"ts":1011310227024},{"cat":"function","dur":44,"name":"void __cdecl Hazel::WindowsWindow::SetVSync(bool)","ph":"X","pid":0,"tid":1026436109,"ts":1011310238302},{"cat":"function","dur":1356529,"name":"void __cdecl Hazel::WindowsWindow::Init(const struct Hazel::WindowProps &)","ph":"X","pid":0,"tid":1026436109,"ts":1011308882413},{"cat":"function","dur":1356598,"name":"__cdecl Hazel::WindowsWindow::WindowsWindow(const struct Hazel::WindowProps &)","ph":"X","pid":0,"tid":1026436109,"ts":1011308882404},{"cat":"function","dur":25,"name":"void __cdecl Hazel::WindowsWindow::SetVSync(bool)","ph":"X","pid":0,"tid":1026436109,"ts":1011310239275},{"cat":"function","dur":9,"name":"void __cdecl Hazel::OpenGLRendererAPI::Init(void)","ph":"X","pid":0,"tid":1026436109,"ts":1011310239355},{"cat":"function","dur":40,"name":"__cdecl Hazel::OpenGLVertexArray::OpenGLVertexArray(void)","ph":"X","pid":0,"tid":1026436109,"ts":1011310239804},{"cat":"function","dur":31,"name":"__cdecl Hazel::OpenGLVertexBuffer::OpenGLVertexBuffer(float *,unsigned int)","ph":"X","pid":0,"tid":1026436109,"ts":1011310240151},{"cat":"function","dur":1,"name":"void __cdecl Hazel::OpenGLVertexBuffer::Bind(void) const","ph":"X","pid":0,"tid":1026436109,"ts":1011310240701},{"cat":"function","dur":478,"name":"void __cdecl Hazel::OpenGLVertexArray::AddVertexBuffer(const class std::shared_ptr<class Hazel::VertexBuffer> &)","ph":"X","pid":0,"tid":1026436109,"ts":1011310240304},{"cat":"function","dur":39,"name":"__cdecl Hazel::OpenGLIndexBuffer::OpenGLIndexBuffer(unsigned int *,unsigned int)","ph":"X","pid":0,"tid":1026436109,"ts":1011310240835},{"cat":"function","dur":0,"name":"void __cdecl Hazel::OpenGLIndexBuffer::Bind(void) const","ph":"X","pid":0,"tid":1026436109,"ts":1011310240928},{"cat":"function","dur":43,"name":"void __cdecl Hazel::OpenGLVertexArray::SetIndexBuffer(const class std::shared_ptr<class Hazel::IndexBuffer> &)","ph":"X","pid":0,"tid":1026436109,"ts":1011310240927},{"cat":"function","dur":38,"name":"__cdecl Hazel::OpenGLTexture2D::OpenGLTexture2D(unsigned int,unsigned int)","ph":"X","pid":0,"tid":1026436109,"ts":1011310241013},{"cat":"function","dur":10,"name":"void __cdecl Hazel::OpenGLTexture2D::SetData(void *,unsigned int)","ph":"X","pid":0,"tid":1026436109,"ts":1011310241142},{"cat":"function","dur":302,"name":"class std::basic_string<char,struct std::char_traits<char>,class std::allocator<char> > __cdecl Hazel::OpenGLShader::ReadFile(const class std::basic_string<char,struct std::char_traits<char>,class std::allocator<char> > &)","ph":"X","pid":0,"tid":1026436109,"ts":1011310241218},{"cat":"function","dur":123,"name":"class std::unordered_map<unsigned int,class std::basic_string<char,struct std::char_traits<char>,class std::allocator<char> >,struct std::hash<unsigned int>,struct std::equal_to<unsigned int>,class std::allocator<struct std::pair<unsigned int const ,class std::basic_string<char,struct std::char_traits<char>,class std::allocator<char> > > > > __cdecl Hazel::OpenGLShader::PreProcess(const class std::basic_string<char,struct std::char_traits<char>,class std::allocator<char> > &)","ph":"X","pid":0,"tid":1026436109,"ts":1011310241572},{"cat":"function","dur":786,"name":"void __cdecl Hazel::OpenGLShader::Compile(const class std::unordered_map<unsigned int,class std::basic_string<char,struct std::char_traits<char>,class std::allocator<char> >,struct std::hash<unsigned int>,struct std::equal_to<unsigned int>,class std::allocator<struct std::pair<unsigned int const ,class std::basic_string<char,struct std::char_traits<char>,class std::allocator<char> > > > > &)","ph":"X","pid":0,"tid":1026436109,"ts":1011310241746},{"cat":"function","dur":1405,"name":"__cdecl Hazel::OpenGLShader::OpenGLShader(const class std::basic_string<char,struct std::char_traits<char>,class std::allocator<char> > &)","ph":"X","pid":0,"tid":1026436109,"ts":1011310241214},{"cat":"function","dur":3,"name":"void __cdecl Hazel::OpenGLShader::Bind(void) const","ph":"X","pid":0,"tid":1026436109,"ts":1011310242721},{"cat":"function","dur":54,"name":"void __cdecl Hazel::OpenGLShader::SetInt(const class std::basic_string<char,struct std::char_traits<char>,class std::allocator<char> > &,int)","ph":"X","pid":0,"tid":1026436109,"ts":1011310242824},{"cat":"function","dur":3576,"name":"void __cdecl Hazel::Renderer2D::Init(void)","ph":"X","pid":0,"tid":1026436109,"ts":1011310239410},{"cat":"function","dur":3698,"name":"void __cdecl Hazel::Renderer::Init(void)","ph":"X","pid":0,"tid":1026436109,"ts":1011310239354},{"cat":"function","dur":596,"name":"void __cdecl Hazel::ImGuiLayer::OnAttach(void)","ph":"X","pid":0,"tid":1026436109,"ts":1011310243148},{"cat":"function","dur":685,"name":"void __cdecl Hazel::Application::PushOverlay(class Hazel::Layer *)","ph":"X","pid":0,"tid":1026436109,"ts":1011310243143},{"cat":"function","dur":1368895,"name":"__cdecl Hazel::Application::Application(void)","ph":"X","pid":0,"tid":1026436109,"ts":1011308875025},{"cat":"function","dur":5,"name":"__cdecl Hazel::OrthographicCamera::OrthographicCamera(float,float,float,float)","ph":"X","pid":0,"tid":1026436109,"ts":1011310244030},{"cat":"function","dur":1042,"name":"stbi_load - OpenGLTexture2D::OpenGLTexture2D(const std::string&)","ph":"X","pid":0,"tid":1026436109,"ts":1011310244133},{"cat":"function","dur":1168,"name":"__cdecl Hazel::OpenGLTexture2D::OpenGLTexture2D(const class std::basic_string<char,struct std::char_traits<char>,class std::allocator<char> > &)","ph":"X","pid":0,"tid":1026436109,"ts":1011310244133},{"cat":"function","dur":1254,"name":"void __cdecl Sandbox2D::OnAttach(void)","ph":"X","pid":0,"tid":1026436109,"ts":1011310244127},{"cat":"function","dur":1337,"name":"void __cdecl Hazel::Application::PushLayer(class Hazel::Layer *)","ph":"X","pid":0,"tid":1026436109,"ts":1011310244116}]}